pdtrain/__init__.py
pdtrain/cli.py
pdtrain/client.py
pdtrain/config.py
pdtrain/commands/__init__.py
pdtrain/commands/artifacts.py
pdtrain/commands/bundle.py
pdtrain/commands/dataset.py
pdtrain/commands/logs.py
pdtrain/commands/pipeline.py
pdtrain/commands/plan.py
pdtrain/commands/quota.py
pdtrain/commands/run.py
pdtrain/commands/template.py
pdtrain/commands/wallet.py
pdtrain/utils/__init__.py
pdtrain/utils/formatters.py
pdtrain/utils/progress.py
pdtrain-0.2.0.dist-info/licenses/LICENSE
pdtrain-0.2.0.dist-info/METADATA
pdtrain-0.2.0.dist-info/WHEEL
pdtrain-0.2.0.dist-info/entry_points.txt
pdtrain-0.2.0.dist-info/top_level.txt
pdtrain-0.2.0.dist-info/RECORD
