Metadata-Version: 2.4
Name: pdtrain
Version: 0.2.0
Summary: Pipedream Training Orchestrator CLI - Train ML models on AWS SageMaker
Author-email: Pipedream <support@pipedream.ai>
License: MIT
Project-URL: Homepage, https://pipedream.in
Project-URL: Documentation, https://pipedream.in
Project-URL: Repository, https://github.com/pipedream/pdtrain
Project-URL: Issues, https://github.com/pipedream/pdtrain/issues
Project-URL: API Keys, https://pipedream.in/api-keys
Keywords: ml,training,sagemaker,pipedream,cli
Classifier: Development Status :: 4 - Beta
Classifier: Intended Audience :: Developers
Classifier: License :: OSI Approved :: MIT License
Classifier: Programming Language :: Python :: 3
Classifier: Programming Language :: Python :: 3.8
Classifier: Programming Language :: Python :: 3.9
Classifier: Programming Language :: Python :: 3.10
Classifier: Programming Language :: Python :: 3.11
Classifier: Topic :: Software Development :: Libraries :: Python Modules
Requires-Python: >=3.8
License-File: LICENSE
Requires-Dist: click>=8.0
Requires-Dist: requests>=2.28
Requires-Dist: rich>=13.0
Requires-Dist: pydantic>=2.0
Requires-Dist: pyyaml>=6.0
Requires-Dist: python-dotenv>=1.0
Provides-Extra: dev
Requires-Dist: pytest>=7.0; extra == "dev"
Requires-Dist: pytest-cov>=4.0; extra == "dev"
Requires-Dist: black>=23.0; extra == "dev"
Requires-Dist: ruff>=0.1.0; extra == "dev"
Requires-Dist: mypy>=1.0; extra == "dev"
Dynamic: license-file
